marvel/__init__.py
marvel/client.py
marvelapi-0.0.1.dist-info/LICENSE
marvelapi-0.0.1.dist-info/METADATA
marvelapi-0.0.1.dist-info/WHEEL
marvelapi-0.0.1.dist-info/entry_points.txt
marvelapi-0.0.1.dist-info/top_level.txt
marvelapi-0.0.1.dist-info/RECORD
