Metadata-Version: 2.1
Name: marvelapi
Version: 0.0.1
Summary: Marvel api client and possible cli
Home-page: https://github.com/bucknerns/marvelapi
Author: Nathan Buckner
Author-email: bucknerns@gmail.com
License: UNKNOWN
Platform: UNKNOWN
Classifier: Development Status :: 3 - Alpha
Classifier: Intended Audience :: Developers
Classifier: Natural Language :: English
Classifier: License :: Other/Proprietary License
Classifier: Operating System :: POSIX :: Linux
Classifier: Programming Language :: Python :: 3 :: Only
Requires-Dist: requests
